<?xml version="1.0" encoding="utf-8" ?>
<dwsync>
<file name="50th.jpg" server="www.duckcreek1419.org/../../../web/" local="131497350278039254" remote="131497554600000000" Dst="2" />
<file name="dcl_logo.jpg" server="www.duckcreek1419.org/../../../web/" local="131497349900448823" remote="131497554600000000" Dst="2" />
<file name="MASONIC LOGO 50TH.jpg" server="www.duckcreek1419.org/../../../web/" local="131497373363998585" remote="131497554600000000" Dst="2" />
<file name="MASONIC LOGO 50TH.psd" server="www.duckcreek1419.org/../../../web/" local="131497366834159640" remote="131497554600000000" Dst="2" />
<file name="MASONIC LOGO 50TH.tif" server="www.duckcreek1419.org/../../../web/" local="131497367903923076" remote="131497554600000000" Dst="2" />
<file name="masonic_logo_50th_small.jpg" server="www.duckcreek1419.org/../../../web/" local="131497374469749947" remote="131497554600000000" Dst="2" />
<file name="masonic_logo_50th_small.jpg" server="www.duckcreek1419.org" local="131497374460000000" remote="131751561600000000" Dst="2" />
<file name="masonic_logo_50th_small.jpg" server="duckcreek1419.org//web/" local="131497374460000000" remote="131581314600000000" Dst="1" />
</dwsync>